[
  {
    "full_name": "Splode/pomotroid",
    "stargazers_count": 2037,
    "open_issues_count": 79,
    "forks_count": 205
  },
  {
    "full_name": "sindresorhus/refined-github",
    "stargazers_count": 16479,
    "open_issues_count": 123,
    "forks_count": 1210
  },
  {
    "full_name": "webhintio/hint",
    "stargazers_count": 3281,
    "open_issues_count": 328,
    "forks_count": 372
  },
  {
    "full_name": "snowpackjs/astro",
    "stargazers_count": 8715,
    "open_issues_count": 118,
    "forks_count": 415
  },
  {
    "full_name": "Liberontissauri/Ball-Physics-With-TypeScript",
    "stargazers_count": 1,
    "open_issues_count": 0,
    "forks_count": 0
  },
  {
    "full_name": "jnv/lists",
    "stargazers_count": 7713,
    "open_issues_count": 0,
    "forks_count": 636
  },
  {
    "full_name": "rossant/awesome-math",
    "stargazers_count": 5465,
    "open_issues_count": 6,
    "forks_count": 747
  },
  {
    "full_name": "nukeop/nuclear",
    "stargazers_count": 7150,
    "open_issues_count": 120,
    "forks_count": 728
  },
  {
    "full_name": "hackerkid/Mind-Expanding-Books",
    "stargazers_count": 7165,
    "open_issues_count": 58,
    "forks_count": 879
  },
  {
    "full_name": "ourjapanlife/findadoc-frontend",
    "stargazers_count": 21,
    "open_issues_count": 48,
    "forks_count": 23
  },
  {
    "full_name": "rsuite/rsuite",
    "stargazers_count": 6362,
    "open_issues_count": 110,
    "forks_count": 699
  },
  {
    "full_name": "BrandonArmand/Binari",
    "stargazers_count": 88,
    "open_issues_count": 13,
    "forks_count": 55
  },
  {
    "full_name": "ChrisKnott/Eel",
    "stargazers_count": 4722,
    "open_issues_count": 156,
    "forks_count": 490
  },
  {
    "full_name": "Liberontissauri/RandomColorPage-with-React",
    "stargazers_count": 1,
    "open_issues_count": 0,
    "forks_count": 0
  },
  {
    "full_name": "Liberontissauri/electron-vue-calculator",
    "stargazers_count": 3,
    "open_issues_count": 0,
    "forks_count": 0
  },
  {
    "full_name": "mauriciosantos/Buckets-JS",
    "stargazers_count": 1184,
    "open_issues_count": 7,
    "forks_count": 114
  },
  {
    "full_name": "emmabostian/developer-portfolios",
    "stargazers_count": 2911,
    "open_issues_count": 6,
    "forks_count": 680
  },
  {
    "full_name": "Liberontissauri/BrainFckInterpreter",
    "stargazers_count": 1,
    "open_issues_count": 2,
    "forks_count": 0
  },
  {
    "full_name": "cerebroapp/cerebro",
    "stargazers_count": 7185,
    "open_issues_count": 130,
    "forks_count": 469
  },
  {
    "full_name": "MarshallOfSound/Google-Play-Music-Desktop-Player-UNOFFICIAL-",
    "stargazers_count": 8458,
    "open_issues_count": 263,
    "forks_count": 830
  },
  {
    "full_name": "laurent22/joplin",
    "stargazers_count": 27233,
    "open_issues_count": 389,
    "forks_count": 2991
  },
  {
    "full_name": "AllToMP3/alltomp3-app",
    "stargazers_count": 1077,
    "open_issues_count": 163,
    "forks_count": 124
  },
  {
    "full_name": "honestbleeps/Reddit-Enhancement-Suite",
    "stargazers_count": 3329,
    "open_issues_count": 617,
    "forks_count": 854
  },
  {
    "full_name": "danistefanovic/build-your-own-x",
    "stargazers_count": 125909,
    "open_issues_count": 207,
    "forks_count": 11579
  },
  {
    "full_name": "therebelrobot/awesome-workshopper",
    "stargazers_count": 922,
    "open_issues_count": 4,
    "forks_count": 41
  },
  {
    "full_name": "kris-hansen/notion-cli",
    "stargazers_count": 56,
    "open_issues_count": 1,
    "forks_count": 8
  },
  {
    "full_name": "LowLevelJavaScript/Learning-Resources",
    "stargazers_count": 25,
    "open_issues_count": 1,
    "forks_count": 0
  },
  {
    "full_name": "samwincott/Internship-Guide",
    "stargazers_count": 315,
    "open_issues_count": 1,
    "forks_count": 40
  },
  {
    "full_name": "remoteintech/remote-jobs",
    "stargazers_count": 17878,
    "open_issues_count": 25,
    "forks_count": 1905
  },
  {
    "full_name": "yanirs/established-remote",
    "stargazers_count": 4972,
    "open_issues_count": 0,
    "forks_count": 415
  }
]