[
  {
    "full_name": "Splode/pomotroid",
    "stargazers_count": 2120,
    "open_issues_count": 81,
    "forks_count": 212
  },
  {
    "full_name": "sindresorhus/refined-github",
    "stargazers_count": 16776,
    "open_issues_count": 136,
    "forks_count": 1220
  },
  {
    "full_name": "webhintio/hint",
    "stargazers_count": 3303,
    "open_issues_count": 338,
    "forks_count": 387
  },
  {
    "full_name": "snowpackjs/astro",
    "stargazers_count": 10205,
    "open_issues_count": 126,
    "forks_count": 493
  },
  {
    "full_name": "Liberontissauri/Ball-Physics-With-TypeScript",
    "stargazers_count": 1,
    "open_issues_count": 0,
    "forks_count": 0
  },
  {
    "full_name": "jnv/lists",
    "stargazers_count": 7841,
    "open_issues_count": 0,
    "forks_count": 642
  },
  {
    "full_name": "rossant/awesome-math",
    "stargazers_count": 5600,
    "open_issues_count": 7,
    "forks_count": 763
  },
  {
    "full_name": "nukeop/nuclear",
    "stargazers_count": 8040,
    "open_issues_count": 135,
    "forks_count": 769
  },
  {
    "full_name": "hackerkid/Mind-Expanding-Books",
    "stargazers_count": 8441,
    "open_issues_count": 56,
    "forks_count": 941
  },
  {
    "full_name": "ourjapanlife/findadoc-frontend",
    "stargazers_count": 21,
    "open_issues_count": 1,
    "forks_count": 23
  },
  {
    "full_name": "rsuite/rsuite",
    "stargazers_count": 6484,
    "open_issues_count": 122,
    "forks_count": 715
  },
  {
    "full_name": "BrandonArmand/Binari",
    "stargazers_count": 89,
    "open_issues_count": 13,
    "forks_count": 53
  },
  {
    "full_name": "ChrisKnott/Eel",
    "stargazers_count": 4795,
    "open_issues_count": 165,
    "forks_count": 498
  },
  {
    "full_name": "Liberontissauri/RandomColorPage-with-React",
    "stargazers_count": 1,
    "open_issues_count": 0,
    "forks_count": 0
  },
  {
    "full_name": "Liberontissauri/electron-vue-calculator",
    "stargazers_count": 3,
    "open_issues_count": 0,
    "forks_count": 0
  },
  {
    "full_name": "mauriciosantos/Buckets-JS",
    "stargazers_count": 1187,
    "open_issues_count": 7,
    "forks_count": 115
  },
  {
    "full_name": "emmabostian/developer-portfolios",
    "stargazers_count": 3048,
    "open_issues_count": 7,
    "forks_count": 718
  },
  {
    "full_name": "Liberontissauri/BrainFckInterpreter",
    "stargazers_count": 1,
    "open_issues_count": 2,
    "forks_count": 0
  },
  {
    "full_name": "cerebroapp/cerebro",
    "stargazers_count": 7220,
    "open_issues_count": 130,
    "forks_count": 470
  },
  {
    "full_name": "MarshallOfSound/Google-Play-Music-Desktop-Player-UNOFFICIAL-",
    "stargazers_count": 8445,
    "open_issues_count": 264,
    "forks_count": 829
  },
  {
    "full_name": "laurent22/joplin",
    "stargazers_count": 27911,
    "open_issues_count": 298,
    "forks_count": 3114
  },
  {
    "full_name": "AllToMP3/alltomp3-app",
    "stargazers_count": 1108,
    "open_issues_count": 164,
    "forks_count": 128
  },
  {
    "full_name": "honestbleeps/Reddit-Enhancement-Suite",
    "stargazers_count": 3360,
    "open_issues_count": 622,
    "forks_count": 857
  },
  {
    "full_name": "danistefanovic/build-your-own-x",
    "stargazers_count": 128564,
    "open_issues_count": 208,
    "forks_count": 11937
  },
  {
    "full_name": "therebelrobot/awesome-workshopper",
    "stargazers_count": 961,
    "open_issues_count": 4,
    "forks_count": 45
  },
  {
    "full_name": "kris-hansen/notion-cli",
    "stargazers_count": 57,
    "open_issues_count": 1,
    "forks_count": 7
  },
  {
    "full_name": "LowLevelJavaScript/Learning-Resources",
    "stargazers_count": 26,
    "open_issues_count": 1,
    "forks_count": 0
  },
  {
    "full_name": "samwincott/Internship-Guide",
    "stargazers_count": 319,
    "open_issues_count": 1,
    "forks_count": 44
  },
  {
    "full_name": "remoteintech/remote-jobs",
    "stargazers_count": 18041,
    "open_issues_count": 33,
    "forks_count": 1928
  },
  {
    "full_name": "yanirs/established-remote",
    "stargazers_count": 5089,
    "open_issues_count": 0,
    "forks_count": 428
  }
]