[
  {
    "full_name": "Splode/pomotroid",
    "stargazers_count": 2088,
    "open_issues_count": 81,
    "forks_count": 210
  },
  {
    "full_name": "sindresorhus/refined-github",
    "stargazers_count": 16651,
    "open_issues_count": 131,
    "forks_count": 1214
  },
  {
    "full_name": "webhintio/hint",
    "stargazers_count": 3297,
    "open_issues_count": 331,
    "forks_count": 380
  },
  {
    "full_name": "snowpackjs/astro",
    "stargazers_count": 9964,
    "open_issues_count": 127,
    "forks_count": 477
  },
  {
    "full_name": "Liberontissauri/Ball-Physics-With-TypeScript",
    "stargazers_count": 1,
    "open_issues_count": 0,
    "forks_count": 0
  },
  {
    "full_name": "jnv/lists",
    "stargazers_count": 7792,
    "open_issues_count": 0,
    "forks_count": 638
  },
  {
    "full_name": "rossant/awesome-math",
    "stargazers_count": 5569,
    "open_issues_count": 7,
    "forks_count": 764
  },
  {
    "full_name": "nukeop/nuclear",
    "stargazers_count": 7228,
    "open_issues_count": 123,
    "forks_count": 737
  },
  {
    "full_name": "hackerkid/Mind-Expanding-Books",
    "stargazers_count": 8408,
    "open_issues_count": 56,
    "forks_count": 937
  },
  {
    "full_name": "ourjapanlife/findadoc-frontend",
    "stargazers_count": 21,
    "open_issues_count": 47,
    "forks_count": 23
  },
  {
    "full_name": "rsuite/rsuite",
    "stargazers_count": 6446,
    "open_issues_count": 123,
    "forks_count": 710
  },
  {
    "full_name": "BrandonArmand/Binari",
    "stargazers_count": 89,
    "open_issues_count": 13,
    "forks_count": 53
  },
  {
    "full_name": "ChrisKnott/Eel",
    "stargazers_count": 4783,
    "open_issues_count": 165,
    "forks_count": 495
  },
  {
    "full_name": "Liberontissauri/RandomColorPage-with-React",
    "stargazers_count": 1,
    "open_issues_count": 0,
    "forks_count": 0
  },
  {
    "full_name": "Liberontissauri/electron-vue-calculator",
    "stargazers_count": 3,
    "open_issues_count": 0,
    "forks_count": 0
  },
  {
    "full_name": "mauriciosantos/Buckets-JS",
    "stargazers_count": 1185,
    "open_issues_count": 7,
    "forks_count": 114
  },
  {
    "full_name": "emmabostian/developer-portfolios",
    "stargazers_count": 2998,
    "open_issues_count": 8,
    "forks_count": 702
  },
  {
    "full_name": "Liberontissauri/BrainFckInterpreter",
    "stargazers_count": 1,
    "open_issues_count": 2,
    "forks_count": 0
  },
  {
    "full_name": "cerebroapp/cerebro",
    "stargazers_count": 7212,
    "open_issues_count": 130,
    "forks_count": 471
  },
  {
    "full_name": "MarshallOfSound/Google-Play-Music-Desktop-Player-UNOFFICIAL-",
    "stargazers_count": 8452,
    "open_issues_count": 263,
    "forks_count": 828
  },
  {
    "full_name": "laurent22/joplin",
    "stargazers_count": 27728,
    "open_issues_count": 292,
    "forks_count": 3093
  },
  {
    "full_name": "AllToMP3/alltomp3-app",
    "stargazers_count": 1093,
    "open_issues_count": 164,
    "forks_count": 127
  },
  {
    "full_name": "honestbleeps/Reddit-Enhancement-Suite",
    "stargazers_count": 3344,
    "open_issues_count": 622,
    "forks_count": 854
  },
  {
    "full_name": "danistefanovic/build-your-own-x",
    "stargazers_count": 128016,
    "open_issues_count": 208,
    "forks_count": 11889
  },
  {
    "full_name": "therebelrobot/awesome-workshopper",
    "stargazers_count": 947,
    "open_issues_count": 4,
    "forks_count": 44
  },
  {
    "full_name": "kris-hansen/notion-cli",
    "stargazers_count": 56,
    "open_issues_count": 1,
    "forks_count": 7
  },
  {
    "full_name": "LowLevelJavaScript/Learning-Resources",
    "stargazers_count": 26,
    "open_issues_count": 1,
    "forks_count": 0
  },
  {
    "full_name": "samwincott/Internship-Guide",
    "stargazers_count": 319,
    "open_issues_count": 1,
    "forks_count": 43
  },
  {
    "full_name": "remoteintech/remote-jobs",
    "stargazers_count": 17973,
    "open_issues_count": 29,
    "forks_count": 1918
  },
  {
    "full_name": "yanirs/established-remote",
    "stargazers_count": 5066,
    "open_issues_count": 0,
    "forks_count": 426
  }
]